binmergetool/__init__.py
binmergetool/__main__.py
binmergetool/binmergetool.py
binmergetool-0.1.1.dist-info/LICENSE
binmergetool-0.1.1.dist-info/METADATA
binmergetool-0.1.1.dist-info/WHEEL
binmergetool-0.1.1.dist-info/RECORD
