Metadata-Version: 2.1
Name: binmergetool
Version: 0.1.1
Summary: Tool for merging binary files together
Home-page: https://github.com/antoinejeanson/binmergetool
License: MIT
Author: Antoine Jeanson
Author-email: anonymous@mail.com
Requires-Python: >=3.11,<4.0
Classifier: License :: OSI Approved :: MIT License
Classifier: Programming Language :: Python :: 3
Classifier: Programming Language :: Python :: 3.11
Project-URL: Repository, https://github.com/antoinejeanson/binmergetool
